fraudincident_extractor/__init__.py
fraudincident_extractor/main.py
fraudincident_extractor/prompts.py
fraudincident_extractor-2025.12.20201423.dist-info/METADATA
fraudincident_extractor-2025.12.20201423.dist-info/WHEEL
fraudincident_extractor-2025.12.20201423.dist-info/top_level.txt
fraudincident_extractor-2025.12.20201423.dist-info/RECORD
