Metadata-Version: 2.4
Name: fraudincident-extractor
Version: 2025.12.20201423
Summary: A new package is designed to analyze user-submitted incident descriptions related to financial frauds, scams, or cybersecurity breaches. It processes the input text to extract structured details such 
Author-email: fraudincident-extractor <hi@eugene.plus>
License: MIT
Project-URL: Homepage, https://github.com/chigwell/fraudincident-extractor
Requires-Python: >=3.9
Requires-Dist: langchain-llm7>=0.0.0
Requires-Dist: llmatch-messages>=0.0.0
Requires-Dist: langchain-core>=0.3.0
